microkeras/__init__.py
microkeras/activations/__init__.py
microkeras/activations/linear.py
microkeras/activations/linear_derivative.py
microkeras/activations/relu.py
microkeras/activations/relu_derivative.py
microkeras/activations/sigmoid.py
microkeras/activations/sigmoid_derivative.py
microkeras/activations/softmax.py
microkeras/datasets/__init__.py
microkeras/datasets/california_housing.parquet
microkeras/datasets/california_housing.py
microkeras/datasets/mnist.parquet
microkeras/datasets/mnist.py
microkeras/layers/__init__.py
microkeras/layers/dense/__init__.py
microkeras/layers/dense/build.py
microkeras/layers/dense/copy.py
microkeras/layers/dense/dense.py
microkeras/layers/dense/initialize.py
microkeras/losses/__init__.py
microkeras/losses/categorical_crossentropy.py
microkeras/losses/mean_squared_error.py
microkeras/losses/mean_squared_error_derivative.py
microkeras/models/__init__.py
microkeras/models/sequential/__init__.py
microkeras/models/sequential/add.py
microkeras/models/sequential/build.py
microkeras/models/sequential/compile.py
microkeras/models/sequential/copy.py
microkeras/models/sequential/evaluate.py
microkeras/models/sequential/fit.py
microkeras/models/sequential/initialize.py
microkeras/models/sequential/load.py
microkeras/models/sequential/predict.py
microkeras/models/sequential/save.py
microkeras/models/sequential/sequential.py
microkeras/operations/__init__.py
microkeras/operations/backward/__init__.py
microkeras/operations/backward/backward.py
microkeras/operations/backward/backward_layer.py
microkeras/operations/backward/calculate_dW.py
microkeras/operations/backward/calculate_dW_wrapper.py
microkeras/operations/backward/calculate_dZ.py
microkeras/operations/backward/calculate_dZ_linear_mean_squared_error.py
microkeras/operations/backward/calculate_dZ_relu_mean_squared_error.py
microkeras/operations/backward/calculate_dZ_softmax_categorical_crossentropy.py
microkeras/operations/backward/calculate_dZ_wrapper.py
microkeras-0.1.4.dist-info/LICENSE
microkeras-0.1.4.dist-info/METADATA
microkeras-0.1.4.dist-info/WHEEL
microkeras-0.1.4.dist-info/top_level.txt
microkeras-0.1.4.dist-info/RECORD
