Metadata-Version: 2.1
Name: microkeras
Version: 0.1.4
License-File: LICENSE
Requires-Dist: mkdocs ==1.6.1
Requires-Dist: mkdocs-autorefs ==1.2.0
Requires-Dist: mkdocs-awesome-pages-plugin ==2.9.3
Requires-Dist: mkdocs-get-deps ==0.2.0
Requires-Dist: mkdocs-material ==9.5.39
Requires-Dist: mkdocs-material-extensions ==1.3.1
Requires-Dist: mkdocstrings ==0.26.1
Requires-Dist: mkdocstrings-python ==1.11.1
Requires-Dist: numpy <2.0,>=1.23
Requires-Dist: pandas <2.3,>=2.0
Requires-Dist: plotly ==5.24.1
Requires-Dist: pytest ==8.3.3
Requires-Dist: scikit-learn ==1.5.2
Requires-Dist: scipy <1.15,>=1.13
Requires-Dist: tqdm ==4.66.5
